MANIFEST.in
license.txt
setup.py
TTFQuery.egg-info/PKG-INFO
TTFQuery.egg-info/SOURCES.txt
TTFQuery.egg-info/dependency_links.txt
TTFQuery.egg-info/top_level.txt
bin/ttffamily
bin/ttffiles
bin/ttfgroups
bin/ttfmetadata
ttfquery/__init__.py
ttfquery/_scriptregistry.py
ttfquery/describe.py
ttfquery/findsystem.py
ttfquery/glyph.py
ttfquery/glyphquery.py
ttfquery/guessdescription.py
ttfquery/ttffamily.py
ttfquery/ttffiles.py
ttfquery/ttfgroups.py
ttfquery/ttfmetadata.py