Metadata-Version: 1.0
Name: TTFQuery
Version: 1.0.5
Summary: FontTools-based package for querying system fonts
Home-page: http://ttfquery.sourceforge.net/
Author: Mike C. Fletcher
Author-email: mcfletch@users.sourceforge.net
License: BSD-style, see license.txt for details
Keywords: fonttools,ttf,truetype,outline,font,curve,system fonts
Platform: Any
Classifier: License :: OSI Approved :: BSD License
Classifier: Programming Language :: Python
Classifier: Topic :: Software Development :: Libraries :: Python Modules
Classifier: Intended Audience :: Developers
Classifier: Operating System :: OS Independent
Classifier: Topic :: Multimedia :: Graphics
